{
	"info": {
		"_postman_id": "3909d0f7-e36b-4f65-9bb9-31265bb6c475",
		"name": "JSON Place Holder",
		"description": "https://jsonplaceholder.typicode.com/",
		"schema": "https://schema.getpostman.com/json/collection/v2.1.0/collection.json"
	}
	"item": [
		{
			"name": "Get posts",
			"request": {
				"method": "GET",
				"header": [],
				"url": {
					"raw": "https://jsonplaceholder.typicode.com/posts",
					"protocol": "https",
					"host": [
						"jsonplaceholder",
						"typicode",
						"com"
					],
					"path": [
						"posts"
					]
				},
				"description": "Return all posts"
			},
			"response": []
		},
		{
			"name": "Get single post",
			"request": {
				"method": "GET",
				"header": [],
				"url": {
					"raw": "https://jsonplaceholder.typicode.com/posts/1",
					"protocol": "https",
					"host": [
						"jsonplaceholder",
						"typicode",
						"com"
					],
					"path": [
						"posts",
						"1"
					]
				},
				"description": "Return one posts by id"
			},
			"response": []
		},
		{
			"name": "Create post",
			"request": {
				"method": "POST",
				"header": [],
				"body": {
					"mode": "raw",
					"raw": "{\"title\": \"foo\",\"body\": \"bar\",\"userId\": 1}",
					"options": {
						"raw": {
							"language": "json"
						}
					}
				},
				"url": {
					"raw": "https://jsonplaceholder.typicode.com/posts",
					"protocol": "https",
					"host": [
						"jsonplaceholder",
						"typicode",
						"com"
					],
					"path": [
						"posts"
					]
				},
				"description": "Add post to DB"
			},
			"response": []
		},
		{
			"name": "Update post",
			"request": {
				"method": "PUT",
				"header": [],
				"body": {
					"mode": "raw",
					"raw": "{\"id\": 1, \"title\": \"foo\",\"body\": \"bar\",\"userId\": 1}",
					"options": {
						"raw": {
							"language": "json"
						}
					}
				},
				"url": {
					"raw": "https://jsonplaceholder.typicode.com/posts/1",
					"protocol": "https",
					"host": [
						"jsonplaceholder",
						"typicode",
						"com"
					],
					"path": [
						"posts",
						"1"
					]
				},
				"description": "Replace post data with new one"
			},
			"response": []
		},
		{
			"name": "Patch post",
			"request": {
				"method": "PATCH",
				"header": [],
				"body": {
					"mode": "raw",
					"raw": "{\"title\": \"foo\",\"body\": \"bar\"}",
					"options": {
						"raw": {
							"language": "json"
						}
					}
				},
				"url": {
					"raw": "https://jsonplaceholder.typicode.com/posts/1",
					"protocol": "https",
					"host": [
						"jsonplaceholder",
						"typicode",
						"com"
					],
					"path": [
						"posts",
						"1"
					]
				},
				"description": "Update post information"
			},
			"response": []
		},
		{
			"name": "Delete post",
			"request": {
				"method": "DELETE",
				"header": [],
				"url": {
					"raw": "https://jsonplaceholder.typicode.com/posts/1",
					"protocol": "https",
					"host": [
						"jsonplaceholder",
						"typicode",
						"com"
					],
					"path": [
						"posts",
						"1"
					]
				},
				"description": "Remove post from DB"
			},
			"response": []
		}
	]
}
